zhmccli/__init__.py
zhmccli/_cmd_adapter.py
zhmccli/_cmd_capacitygroup.py
zhmccli/_cmd_certificates.py
zhmccli/_cmd_character_rule.py
zhmccli/_cmd_console.py
zhmccli/_cmd_cpc.py
zhmccli/_cmd_hba.py
zhmccli/_cmd_imageprofile.py
zhmccli/_cmd_info.py
zhmccli/_cmd_ldap_server_definition.py
zhmccli/_cmd_loadprofile.py
zhmccli/_cmd_lpar.py
zhmccli/_cmd_metrics.py
zhmccli/_cmd_nic.py
zhmccli/_cmd_partition.py
zhmccli/_cmd_password_rule.py
zhmccli/_cmd_port.py
zhmccli/_cmd_resetprofile.py
zhmccli/_cmd_session.py
zhmccli/_cmd_storagegroup.py
zhmccli/_cmd_storagevolume.py
zhmccli/_cmd_unmanaged_cpc.py
zhmccli/_cmd_user.py
zhmccli/_cmd_user_pattern.py
zhmccli/_cmd_user_role.py
zhmccli/_cmd_vfunction.py
zhmccli/_cmd_vstorageresource.py
zhmccli/_cmd_vswitch.py
zhmccli/_helper.py
zhmccli/_session_file.py
zhmccli/_version.py
zhmccli/_version_scm.py
zhmccli/zhmccli.py
zhmccli-1.13.1.dist-info/licenses/AUTHORS.md
zhmccli-1.13.1.dist-info/licenses/LICENSE
zhmccli-1.13.1.dist-info/METADATA
zhmccli-1.13.1.dist-info/WHEEL
zhmccli-1.13.1.dist-info/entry_points.txt
zhmccli-1.13.1.dist-info/top_level.txt
zhmccli-1.13.1.dist-info/zip-safe
zhmccli-1.13.1.dist-info/RECORD
