Metadata-Version: 2.4
Name: zhmccli
Version: 1.13.1
Summary: A CLI for the IBM Z HMC, written in pure Python
Author-email: Juergen Leopold <leopoldj@de.ibm.com>, Andreas Maier <maiera@de.ibm.com>
Maintainer-email: Andreas Maier <maiera@de.ibm.com>, Kathir Velusamy <kathir.velu@in.ibm.com'>
License: Apache License, Version 2.0
Project-URL: Homepage, https://github.com/zhmcclient/zhmccli
Project-URL: Bug Tracker, https://github.com/zhmcclient/zhmccli/issues
Project-URL: Documentation, https://zhmccli.readthedocs.io/en/stable/
Project-URL: Source Code, https://github.com/zhmcclient/zhmccli
Project-URL: Changelog, https://zhmccli.readthedocs.io/en/stable/changes.html
Keywords: hmc,prometheus,monitoring
Platform: any
Classifier: License :: OSI Approved :: Apache Software License
Classifier: Development Status :: 5 - Production/Stable
Classifier: Intended Audience :: Information Technology
Classifier: Topic :: System :: Systems Administration
Classifier: Environment :: Console
Classifier: Operating System :: OS Independent
Classifier: Programming Language :: Python :: 3
Classifier: Programming Language :: Python :: 3.8
Classifier: Programming Language :: Python :: 3.9
Classifier: Programming Language :: Python :: 3.10
Classifier: Programming Language :: Python :: 3.11
Classifier: Programming Language :: Python :: 3.12
Classifier: Programming Language :: Python :: 3.13
Requires-Python: >=3.8
License-File: LICENSE
License-File: AUTHORS.md
Requires-Dist: zhmcclient>=1.21.0
Requires-Dist: click>=8.0.2
Requires-Dist: click-repl>=0.2
Requires-Dist: click-spinner>=0.1.6; python_version <= "3.11"
Requires-Dist: click-spinner>=0.1.10; python_version >= "3.12"
Requires-Dist: progressbar2>=3.12.0
Requires-Dist: tabulate>=0.8.2; python_version <= "3.9"
Requires-Dist: tabulate>=0.8.8; python_version >= "3.10"
Requires-Dist: python-dateutil>=2.8.2
Requires-Dist: click-option-group>=0.5.6
Requires-Dist: prompt-toolkit>=3.0.13
Requires-Dist: PyYAML>=6.0.2
Requires-Dist: jsonschema>=4.18.0
Requires-Dist: yamlloader>=0.5.5
Requires-Dist: urllib3>=2.2.3; python_version == "3.8"
Requires-Dist: urllib3>=2.5.0; python_version >= "3.9"
Requires-Dist: pyrsistent>=0.20.0
Dynamic: license-file
